hyve_examples/__init__.py
hyve_examples/retrieval.py
hyve_examples/data/Glasser_2016.32k.L.label.gii
hyve_examples/data/Glasser_2016.32k.R.label.gii
hyve_examples/data/Gordon.32k.L.label.gii
hyve_examples/data/Gordon.32k.R.label.gii
hyve_examples/data/IC_01.nii.gz
hyve_examples/data/MSC_ward400_parcellation.nii.gz
hyve_examples/data/S1200.L.flat.32k_fs_LR.surf.gii
hyve_examples/data/S1200.R.flat.32k_fs_LR.surf.gii
hyve_examples/data/atlas-schaefer400_desc-synth_cov.tsv
hyve_examples/data/cuboid.svg
hyve_examples/data/desc-schaefer_res-0400_atlas.nii
hyve_examples/data/lh.curv
hyve_examples/data/lh.inflated
hyve_examples/data/myconnectome_ward400_parcellation.nii.gz
hyve_examples/data/nullexample.nii
hyve_examples/data/nullexample_L.gii
hyve_examples/data/nullexample_R.gii
hyve_examples/data/pain_thresh_cFWE05.nii.gz
hyve_examples/data/rh.curv
hyve_examples/data/rh.inflated
hyve_examples/data/tpl-fsLR_hemi-L_desc-schaefer_res-400_atlas.gii
hyve_examples/data/tpl-fsLR_hemi-R_desc-schaefer_res-400_atlas.gii
hyve_examples/data/tpl-fsaverage_hemi-L_desc-schaefer_res-400_atlas.gii
hyve_examples/data/tpl-fsaverage_hemi-R_desc-schaefer_res-400_atlas.gii
hyve_examples/data/ve_fig-blendInsert.svg
hyve_examples-0.0.1.dist-info/LICENSE
hyve_examples-0.0.1.dist-info/METADATA
hyve_examples-0.0.1.dist-info/WHEEL
hyve_examples-0.0.1.dist-info/top_level.txt
hyve_examples-0.0.1.dist-info/RECORD
